Workbook
Name CASE: [1]LBO!$E$7
Name CASE: DCF!#REF!
Name CIRC: [1]LBO!$E$6
Name CIRC: DCF!#REF!
Name PIK: [1]LBO!$E$8
Name tgr: [2]DCF!$E$19
Name wacc: [2]DCF!$E$18

Sheet Cover
B2: Cover
A4: x | B4: Simple DCF Tutorial | H4: Amazon Advanced DCF - Part 1 | N4: Amazon Advanced DCF - Part 2
B5: https://youtu.be/nyot7FkYoqM | H5: https://youtube.com/live/fmoE3H8RjP4 | N5: TBU
B6: - DCF Concepts | H6: - Revenue Build | N6: - Projections for Revenue and EBIT
B7: - Projecting FCF | H7: - EBIT Build | N7: - Multiple Scenarios
B8: - Terminal Value | H8: - Project FCF | N8: - Gather Historical Cash Flow Items
B9: - Discounting to Present Value | H9: - WACC | N9: - Sum-of-the-parts DCF
H10: - Mid-Year Convention | N10: - Terminal Value - Perpetuity and Exit Multiple
H11: - Terminal Value | N11: - Levering / Unlevering Beta
H12: - Diluted Shares | N12: - Sensitivity Tables
A14: x | B14: Notes
B15: This model will be available FOR FREE to download after this steam ends (see description)
B16: Sign up for my NEW discord channel | G16: https://discord.gg/AHnxBUGTwt
B17: Sign up for my investment banking course | G17: https://forms.gle/wt4cZrezbxVgNzGUA
B19: Investment Banking Playlist | G19: https://www.youtube.com/watch?v=hQfLWritg9s&list=PL71QplJWp1RoobXOSA77YooScaVYmPojv
B20: Modeling Tutorials Playlist | G20: https://www.youtube.com/playlist?list=PL71QplJWp1RoaKEMTo_9CZA-kyjwT5rGo
B21: Private Equity Video Playlist | G21: https://www.youtube.com/playlist?list=PL71QplJWp1Rrm0dkWjjIY2cf4jTYSU0t2
B22: Paper LBO Tutorial | G22: https://youtu.be/iS0isM0f2z8
B23: Simple LBO Tutorial | G23: https://youtu.be/zeCfu5g0Uis
B24: Excel Shortcuts for Finance and Modeling | G24: https://youtu.be/oDjhg57XH-A
A26: x | B26: rareliquid (AKA the guy who created this model)
B28: YouTube | G28: https://www.youtube.com/@rareliquid
B29: Instagram | G29: https://www.instagram.com/rareliquid
B30: TikTok | G30: https://www.tiktok.com/@rareliquid
B31: Twitter | G31: https://www.twitter.com/rareliquid
B32: LinkedIn | G32: https://www.linkedin.com/in/benchon

Sheet DCF
B2: DCF
A4: x | B4: Ticker | L4: AMZN
B5: Date | L5: 45534
B6: End of Year | L6: 45657
A8: x | B8: Assumptions
B10: WACC | L10: =WACC!F22 -> 0.08438986
B11: TGR | L11: 0.025
A13: x | B13: Financials
A15: x | B15: Revenue | C15: 2015 | D15: =C15+1 -> 2016 | E15: =D15+1 -> 2017 | F15: =E15+1 -> 2018 | G15: =F15+1 -> 2019 | H15: =G15+1 -> 2020 | I15: =H15+1 -> 2021 | J15: =I15+1 -> 2022 | K15: =J15+1 -> 2023 | ... Q15: =P15+1 -> 2029
B17: North America | C17: =Segments!C6 -> 63708 | D17: =Segments!D6 -> 79785 | E17: =Segments!E6 -> 106110 | F17: =Segments!F6 -> 141366 | G17: =Segments!G6 -> 170773 | H17: =Segments!H6 -> 236282 | I17: =Segments!I6 -> 279833 | J17: =Segments!J6 -> 315880 | ... Q17: =Segments!Q6 -> 590847
B18: % growth | C18: =IF(ISERROR(C17/B17-1),"--",C17/B17-1) -> -- | D18: =IF(ISERROR(D17/C17-1),"--",D17/C17-1) -> 0.25235449 | E18: =IF(ISERROR(E17/D17-1),"--",E17/D17-1) -> 0.32994924 | F18: =IF(ISERROR(F17/E17-1),"--",F17/E17-1) -> 0.33225898 | G18: =IF(ISERROR(G17/F17-1),"--",G17/F17-1) -> 0.20802032 | H18: =IF(ISERROR(H17/G17-1),"--",H17/G17-1) -> 0.38360279 | I18: =IF(ISERROR(I17/H17-1),"--",I17/H17-1) -> 0.18431789 | K18: =IF(ISERROR(K17/J17-1),"--",K17/J17-1) -> 0.11696847 | L18: =IF(ISERROR(L17/K17-1),"--",L17/K17-1) -> 0.095851236 | M18: =IF(ISERROR(M17/L17-1),"--",M17/L17-1) -> 0.095213463 | N18: =IF(ISERROR(N17/M17-1),"--",N17/M17-1) -> 0.089760332 | O18: =IF(ISERROR(O17/N17-1),"--",O17/N17-1) -> 0.077892219 | P18: =IF(ISERROR(P17/O17-1),"--",P17/O17-1) -> 0.098287952 | Q18: =IF(ISERROR(Q17/P17-1),"--",Q17/P17-1) -> 0.08153123
B19: % of total sales | C19: =C17/C$29 -> 0.59536848 | D19: =D17/D$29 -> 0.58671049 | E19: =E17/E$29 -> 0.5965727 | F19: =F17/F$29 -> 0.60701542 | G19: =G17/G$29 -> 0.60876865 | H19: =H17/H$29 -> 0.61202806 | I19: =I17/I$29 -> 0.59561494 | J19: =J17/J$29 -> 0.61457286 | ... Q19: =Q17/Q$29 -> 0.55955871
B21: International | C21: =Segments!C8 -> 35418 | D21: =Segments!D8 -> 43983 | E21: =Segments!E8 -> 54297 | F21: =Segments!F8 -> 65866 | G21: =Segments!G8 -> 74723 | H21: =Segments!H8 -> 104412 | I21: =Segments!I8 -> 127787 | J21: =Segments!J8 -> 118007 | ... Q21: =Segments!Q8 -> 215930
B22: % growth | C22: =IF(ISERROR(C21/B21-1),"--",C21/B21-1) -> -- | D22: =IF(ISERROR(D21/C21-1),"--",D21/C21-1) -> 0.24182619 | E22: =IF(ISERROR(E21/D21-1),"--",E21/D21-1) -> 0.23449969 | F22: =IF(ISERROR(F21/E21-1),"--",F21/E21-1) -> 0.21306886 | G22: =IF(ISERROR(G21/F21-1),"--",G21/F21-1) -> 0.13446998 | H22: =IF(ISERROR(H21/G21-1),"--",H21/G21-1) -> 0.39732077 | I22: =IF(ISERROR(I21/H21-1),"--",I21/H21-1) -> 0.22387273 | J22: =IF(ISERROR(J21/I21-1),"--",J21/I21-1) -> -0.076533607 | ... Q22: =IF(ISERROR(Q21/P21-1),"--",Q21/P21-1) -> 0.08281181
B23: % of total sales | C23: =C21/C$29 -> 0.33099079 | D23: =D21/D$29 -> 0.32343533 | E23: =E21/E$29 -> 0.30526914 | F23: =F21/F$29 -> 0.28282386 | G23: =G21/G$29 -> 0.26637126 | H23: =H21/H$29 -> 0.27045257 | I23: =I21/I$29 -> 0.27199024 | J23: =J21/J$29 -> 0.2295932 | ... Q23: =Q21/Q$29 -> 0.20449543
B25: AWS | C25: =Segments!C9 -> 7880 | D25: =Segments!D9 -> 12219 | E25: =Segments!E9 -> 17459 | F25: =Segments!F9 -> 25655 | G25: =Segments!G9 -> 35026 | H25: =Segments!H9 -> 45370 | I25: =Segments!I9 -> 62202 | J25: =Segments!J9 -> 80096 | ... Q25: =Segments!Q9 -> 249139
B26: % growth | C26: =IF(ISERROR(C25/B25-1),"--",C25/B25-1) -> -- | D26: =IF(ISERROR(D25/C25-1),"--",D25/C25-1) -> 0.55063452 | E26: =IF(ISERROR(E25/D25-1),"--",E25/D25-1) -> 0.42884033 | F26: =IF(ISERROR(F25/E25-1),"--",F25/E25-1) -> 0.46944269 | G26: =IF(ISERROR(G25/F25-1),"--",G25/F25-1) -> 0.36526993 | H26: =IF(ISERROR(H25/G25-1),"--",H25/G25-1) -> 0.29532347 | I26: =IF(ISERROR(I25/H25-1),"--",I25/H25-1) -> 0.37099405 | J26: =IF(ISERROR(J25/I25-1),"--",J25/I25-1) -> 0.28767564 | ... Q26: =IF(ISERROR(Q25/P25-1),"--",Q25/P25-1) -> 0.19362891
B27: % of total sales | C27: =C25/C$29 -> 0.07364073 | D27: =D25/D$29 -> 0.089854177 | E27: =E25/E$29 -> 0.098158164 | F27: =F25/F$29 -> 0.11016072 | G27: =G25/G$29 -> 0.12486008 | H27: =H25/H$29 -> 0.11751938 | I27: =I25/I$29 -> 0.13239482 | J27: =J25/J$29 -> 0.15583395 | ... Q27: =Q25/Q$29 -> 0.23594585
B29: Total | C29: =C17+C21+C25 -> 107006 | D29: =D17+D21+D25 -> 135987 | E29: =E17+E21+E25 -> 177866 | F29: =F17+F21+F25 -> 232887 | G29: =G17+G21+G25 -> 280522 | H29: =H17+H21+H25 -> 386064 | I29: =I17+I21+I25 -> 469822 | J29: =J17+J21+J25 -> 513983 | ... Q29: =Q17+Q21+Q25 -> 1055916
B30: % growth | C30: =IF(ISERROR(C29/B29-1),"--",C29/B29-1) -> -- | D30: =IF(ISERROR(D29/C29-1),"--",D29/C29-1) -> 0.27083528 | E30: =IF(ISERROR(E29/D29-1),"--",E29/D29-1) -> 0.30796326 | F30: =IF(ISERROR(F29/E29-1),"--",F29/E29-1) -> 0.30933962 | G30: =IF(ISERROR(G29/F29-1),"--",G29/F29-1) -> 0.20454126 | H30: =IF(ISERROR(H29/G29-1),"--",H29/G29-1) -> 0.37623431 | I30: =IF(ISERROR(I29/H29-1),"--",I29/H29-1) -> 0.21695367 | J30: =IF(ISERROR(J29/I29-1),"--",J29/I29-1) -> 0.093995173 | ... Q30: =IF(ISERROR(Q29/P29-1),"--",Q29/P29-1) -> 0.10631298
A32: x | B32: EBIT | C32: 2015 | D32: 2016 | E32: 2017 | F32: 2018 | G32: 2019 | H32: 2020 | I32: 2021 | J32: 2022 | K32: 2023 | L32: 2024 | M32: 2025 | N32: 2026 | O32: 2027 | P32: 2028 | Q32: 2029
B34: North America | C34: =Segments!C12 -> 2751 | D34: =Segments!D12 -> 4099 | E34: =Segments!E12 -> 2837 | F34: =Segments!F12 -> 7267 | G34: =Segments!G12 -> 7033 | H34: =Segments!H12 -> 8651 | I34: =Segments!I12 -> 7271 | J34: =Segments!J12 -> -2847 | ... N34: =Segments!N12 -> 34190 | O34: =O35*O17 -> 36853.135 | P34: =P35*P17 -> 40475.354 | Q34: =Q35*Q17 -> 43775.36
B35: % of sales | C35: =C34/C17 -> 0.04318139 | D35: =D34/D17 -> 0.051375572 | E35: =E34/E17 -> 0.026736406 | F35: =F34/F17 -> 0.051405571 | G35: =G34/G17 -> 0.041183325 | H35: =H34/H17 -> 0.03661303 | I35: =I34/I17 -> 0.025983354 | J35: =J34/J17 -> -0.0090129163 | ... N35: =N34/N17 -> 0.074089163 | O35: =N35 -> 0.074089163 | P35: =O35 -> 0.074089163 | Q35: =P35 -> 0.074089163
B36: % of total EBIT | C36: =C34/C$46 -> 0.60822463 | D36: =D34/D$46 -> 0.55936135 | E36: =E34/E$46 -> 0.69094009 | F36: =F34/F$46 -> 0.58505756 | G36: =G34/G$46 -> 0.48366687 | H36: =H34/H$46 -> 0.37778942 | I36: =I34/I$46 -> 0.29225451 | J36: =J34/J$46 -> -0.23244611 | ... Q36: =Q34/Q$46 -> 0.27652694
B38: International | C38: =Segments!C14 -> -91 | D38: =Segments!D14 -> -477 | E38: =Segments!E14 -> -3062 | F38: =Segments!F14 -> -2142 | G38: =Segments!G14 -> -1693 | H38: =Segments!H14 -> 717 | I38: =Segments!I14 -> -924 | J38: =Segments!J14 -> -7746 | ... N38: =Segments!N14 -> 9726 | O38: =O39*O21 -> 10911.071 | P38: =P39*P21 -> 11295.389 | Q38: =Q39*Q21 -> 12230.781
B39: % of sales | C39: =C38/C21 -> -0.002569315 | D39: =D38/D21 -> -0.010845099 | E39: =E38/E21 -> -0.056393539 | F39: =F38/F21 -> -0.032520572 | G39: =G38/G21 -> -0.022657013 | H39: =H38/H21 -> 0.0068670268 | I39: =I38/I21 -> -0.0072307825 | J39: =J38/J21 -> -0.065640174 | ... N39: =N38/N21 -> 0.056642343 | O39: =N39 -> 0.056642343 | P39: =O39 -> 0.056642343 | Q39: =P39 -> 0.056642343
B40: % of total EBIT | C40: =C38/C$46 -> -0.02011939 | D40: =D38/D$46 -> -0.065092795 | E40: =E38/E$46 -> -0.74573794 | F40: =F38/F$46 -> -0.17244988 | G40: =G38/G$46 -> -0.11642941 | H40: =H38/H$46 -> 0.031311411 | I40: =I38/I$46 -> -0.037139756 | J40: =J38/J$46 -> -0.63242978 | ... Q40: =Q38/Q$46 -> 0.077261283
B42: AWS | C42: =Segments!C15 -> 1863 | D42: =Segments!D15 -> 3706 | E42: =Segments!E15 -> 4331 | F42: =Segments!F15 -> 7296 | G42: =Segments!G15 -> 9201 | H42: =Segments!H15 -> 13531 | I42: =Segments!I15 -> 18532 | J42: =Segments!J15 -> 22841 | ... Q42: =Segments!Q15 -> 102298
B43: % of sales | C43: =C42/C25 -> 0.23642132 | D43: =D42/D25 -> 0.30329814 | E43: =E42/E25 -> 0.2480669 | F43: =F42/F25 -> 0.28438901 | G43: =G42/G25 -> 0.26269057 | H43: =H42/H25 -> 0.29823672 | I43: =I42/I25 -> 0.29793254 | J43: =J42/J25 -> 0.2851703 | ... Q43: =Q42/Q25 -> 0.41060613
B44: % of total EBIT | C44: =C42/C$46 -> 0.41189476 | D44: =D42/D$46 -> 0.50573144 | E44: =E42/E$46 -> 1.0547979 | F44: =F42/F$46 -> 0.58739232 | G44: =G42/G$46 -> 0.63276253 | H44: =H42/H$46 -> 0.59089917 | I44: =I42/I$46 -> 0.74488524 | J44: =J42/J$46 -> 1.8648759 | ... Q44: =Q42/Q$46 -> 0.64621178
B46: Total | C46: =C34+C38+C42 -> 4523 | D46: =D34+D38+D42 -> 7328 | E46: =E34+E38+E42 -> 4106 | F46: =F34+F38+F42 -> 12421 | G46: =G34+G38+G42 -> 14541 | H46: =H34+H38+H42 -> 22899 | I46: =I34+I38+I42 -> 24879 | J46: =J34+J38+J42 -> 12248 | ... Q46: =Q34+Q38+Q42 -> 158304.14
B47: % of sales | C47: =C46/C29 -> 0.042268658 | D47: =D46/D29 -> 0.053887504 | E47: =E46/E29 -> 0.023084794 | F47: =F46/F29 -> 0.053334879 | G47: =G46/G29 -> 0.051835507 | H47: =H46/H29 -> 0.059314 | I47: =I46/I29 -> 0.052954098 | J47: =J46/J29 -> 0.023829582 | ... Q47: =Q46/Q29 -> 0.14992115
A49: x | B49: Tax Rate | C49: 2015 | D49: 2016 | E49: 2017 | F49: 2018 | G49: 2019 | H49: 2020 | I49: 2021 | J49: 2022 | K49: 2023 | L49: 2024 | M49: 2025 | N49: 2026 | O49: 2027 | P49: 2028 | Q49: 2029
B51: Taxes | C51: =IS!C31 -> 950 | D51: =IS!D31 -> 1425 | E51: =IS!E31 -> 769 | F51: =IS!F31 -> 1197 | G51: =IS!G31 -> 2374 | H51: =IS!H31 -> 2863 | I51: =IS!I31 -> 4791 | J51: =IS!J31 -> -3217 | ... L51: =IS!L31 -> 9602
B52: % tax rate | C52: =IF(C51<0,"--",IS!C31/IS!C30) -> 0.60586735 | D52: =IF(D51<0,"--",IS!D31/IS!D30) -> 0.36613566 | E52: =IF(E51<0,"--",IS!E31/IS!E30) -> 0.2020494 | F52: =IF(F51<0,"--",IS!F31/IS!F30) -> 0.10629607 | G52: =IF(G51<0,"--",IS!G31/IS!G30) -> 0.16986262 | H52: =IF(H51<0,"--",IS!H31/IS!H30) -> 0.11841343 | I52: =IF(I51<0,"--",IS!I31/IS!I30) -> 0.12557993 | J52: =IF(J51<0,"--",IS!J31/IS!J30) -> -- | ... L52: =IF(L51<0,"--",IS!L31/IS!L30) -> 0.1774763 | M52: =AVERAGE(H52:L52) -> 0.15276204 | N52: =AVERAGE(I52:M52) -> 0.16134919 | O52: =AVERAGE(J52:N52) -> 0.17029151 | P52: =AVERAGE(K52:O52) -> 0.17029151 | Q52: =AVERAGE(L52:P52) -> 0.16643411
A54: x | B54: Cash Flow Items | C54: 2015 | D54: =C54+1 -> 2016 | E54: =D54+1 -> 2017 | F54: =E54+1 -> 2018 | G54: =F54+1 -> 2019 | H54: =G54+1 -> 2020 | I54: =H54+1 -> 2021 | J54: =I54+1 -> 2022 | K54: =J54+1 -> 2023 | ... Q54: =P54+1 -> 2029
B56: D&A | C56: =CFS!C12 -> 5646 | D56: =CFS!D12 -> 7482 | E56: =CFS!E12 -> 10933 | F56: =CFS!F12 -> 15341 | G56: =CFS!G12 -> 21789 | H56: =CFS!H12 -> 25251 | I56: =CFS!I12 -> 34296 | J56: =CFS!J12 -> 41921 | ... L56: =CFS!L12 -> 49673 | M56: =M57*M$29 -> 54029.981 | N56: =N57*N$29 -> 61832.179 | O56: =O57*O$29 -> 69279.715 | P56: =P57*P$29 -> 75991.022 | Q56: =Q57*Q$29 -> 83004.43
B57: % of sales | C57: =C56/C$29 -> 0.052763396 | D57: =D56/D$29 -> 0.055019965 | E57: =E56/E$29 -> 0.061467622 | F57: =F56/F$29 -> 0.065873149 | G57: =G56/G$29 -> 0.077673052 | H57: =H56/H$29 -> 0.065406254 | I57: =I56/I$29 -> 0.072997859 | J57: =J56/J$29 -> 0.081561063 | ... L57: =L56/L$29 -> 0.078145697 | M57: =AVERAGE(H57:L57) -> 0.076554767 | N57: =AVERAGE(I57:M57) -> 0.078784469 | O57: =AVERAGE(J57:N57) -> 0.079941792 | P57: =AVERAGE(K57:O57) -> 0.079617937 | Q57: =AVERAGE(L57:P57) -> 0.078608933
B58: % of CapEx | C58: =C56/C60 -> 1.2303334 | D58: =D56/D60 -> 1.1105833 | E58: =E56/E60 -> 0.91451276 | F58: =F56/F60 -> 1.1425486 | G58: =G56/G60 -> 1.2922721 | H58: =H56/H60 -> 0.62907324 | I58: =I56/I60 -> 0.56174144 | J58: =J56/J60 -> 0.65866918 | ... L58: =L56/L60 -> 0.83327182
B60: CapEx | C60: =-CFS!C27 -> 4589 | D60: =-CFS!D27 -> 6737 | E60: =-CFS!E27 -> 11955 | F60: =-CFS!F27 -> 13427 | G60: =-CFS!G27 -> 16861 | H60: =-CFS!H27 -> 40140 | I60: =-CFS!I27 -> 61053 | J60: =-CFS!J27 -> 63645 | ... L60: =-CFS!L27 -> 59612 | M60: =M61*M$29 -> 76684.249 | N60: =N61*N$29 -> 86008.94 | O60: =O61*O$29 -> 91444.552 | P60: =P61*P$29 -> 97215.974 | Q60: =Q61*Q$29 -> 109688.26
B61: % of sales | C61: =C60/C$29 -> 0.042885446 | D61: =D60/D$29 -> 0.0495415 | E61: =E60/E$29 -> 0.06721352 | F61: =F60/F$29 -> 0.057654571 | G61: =G60/G$29 -> 0.060105803 | H61: =H60/H$29 -> 0.1039724 | I61: =I60/I$29 -> 0.12994921 | J61: =J60/J$29 -> 0.12382705 | ... L61: =L60/L$29 -> 0.093781759 | M61: =AVERAGE(H61:L61) -> 0.10865347 | N61: =AVERAGE(I61:M61) -> 0.10958968 | O61: =AVERAGE(J61:N61) -> 0.10551777 | P61: =AVERAGE(K61:O61) -> 0.10185592 | Q61: =AVERAGE(L61:P61) -> 0.10387972
B63: Change in NWC | C63: =CFS!C19 -> 2557 | D63: =CFS!D19 -> 3916 | E63: =CFS!E19 -> -173 | F63: =CFS!F19 -> -1043 | G63: =CFS!G19 -> -2438 | H63: =CFS!H19 -> 13481 | I63: =CFS!I19 -> -19611 | J63: =CFS!J19 -> -20886 | ... L63: =CFS!L19 -> -6898 | M63: =M64*M$29 -> -11064.85 | N63: =N64*N$29 -> -20246.247 | O63: =O64*O$29 -> -19592.903 | P63: =P64*P$29 -> -18137.108 | Q63: =Q64*Q$29 -> -19838.074
B64: % of sales | C64: =C63/C$29 -> 0.023895856 | D64: =D63/D$29 -> 0.02879687 | E64: =E63/E$29 -> -0.00097264233 | F64: =F63/F$29 -> -0.0044785669 | G64: =G63/G$29 -> -0.0086909405 | H64: =H63/H$29 -> 0.034919081 | I64: =I63/I$29 -> -0.04174134 | J64: =J63/J$29 -> -0.040635585 | ... L64: =L63/L$29 -> -0.010851952 | M64: =AVERAGE(H64:L64) -> -0.015677722 | N64: =AVERAGE(I64:M64) -> -0.025797082 | O64: =AVERAGE(J64:N64) -> -0.022608231 | P64: =AVERAGE(K64:O64) -> -0.01900276 | Q64: =AVERAGE(L64:P64) -> -0.018787549
B65: % of change in sales | C65: -- | D65: =D63/(D29-C29) -> 0.13512301 | E65: =E63/(E29-D29) -> -0.0041309487 | F65: =F63/(F29-E29) -> -0.018956398 | G65: =G63/(G29-F29) -> -0.051180854 | H65: =H63/(H29-G29) -> 0.12773114 | I65: =I63/(I29-H29) -> -0.23413883 | J65: =J63/(J29-I29) -> -0.47295125 | K65: =K63/(K29-J29) -> -0.18981284 | L65: =L63/(L29-K29) -> -0.11334023
A67: x | B67: DCF
A69: x | B69: 12/31 FYE | C69: 2015 | D69: =C69+1 -> 2016 | E69: =D69+1 -> 2017 | F69: =E69+1 -> 2018 | G69: =F69+1 -> 2019 | H69: =G69+1 -> 2020 | I69: =H69+1 -> 2021 | J69: =I69+1 -> 2022 | K69: =J69+1 -> 2023 | ... Q69: =P69+1 -> 2029
B71: Revenue | L71: =L29 -> 635646 | M71: =M29 -> 705769 | N71: =N29 -> 784827 | O71: =O29 -> 866627 | P71: =P29 -> 954446 | Q71: =Q29 -> 1055916
B72: % growth | L72: =L30 -> 0.10588481 | M72: =M30 -> 0.11031769 | N72: =N30 -> 0.11201682 | O72: =O30 -> 0.10422679 | P72: =P30 -> 0.10133425 | Q72: =Q30 -> 0.10631298
B74: EBIT | L74: =L46 -> 62270.17 | M74: =M46 -> 77775.41 | N74: =N46 -> 97823.1 | O74: =O46 -> 118182.71 | P74: =P46 -> 136838.24 | Q74: =Q46 -> 158304.14
B75: % of sales | L75: =L47 -> 0.097963599 | M75: =M47 -> 0.11019953 | N75: =N47 -> 0.12464288 | O75: =O47 -> 0.1363709 | P75: =P47 -> 0.14336929 | Q75: =Q47 -> 0.14992115
B77: Taxes | L77: =L74*L78 -> 11051.479 | M77: =M74*M78 -> 11881.13 | N77: =N74*N78 -> 15783.678 | O77: =O74*O78 -> 20125.511 | P77: =P74*P78 -> 23302.391 | Q77: =Q74*Q78 -> 26347.209
B78: % tax rate | L78: =L52 -> 0.1774763 | M78: =M52 -> 0.15276204 | N78: =N52 -> 0.16134919 | O78: =O52 -> 0.17029151 | P78: =P52 -> 0.17029151 | Q78: =Q52 -> 0.16643411
B80: EBIAT | L80: =L74-L77 -> 51218.691 | M80: =M74-M77 -> 65894.28 | N80: =N74-N77 -> 82039.422 | O80: =O74-O77 -> 98057.195 | P80: =P74-P77 -> 113535.85 | Q80: =Q74-Q77 -> 131956.93
B82: D&A | L82: =L56 -> 49673 | M82: =M56 -> 54029.981 | N82: =N56 -> 61832.179 | O82: =O56 -> 69279.715 | P82: =P56 -> 75991.022 | Q82: =Q56 -> 83004.43
B83: % of sales | L83: =L57 -> 0.078145697 | M83: =M57 -> 0.076554767 | N83: =N57 -> 0.078784469 | O83: =O57 -> 0.079941792 | P83: =P57 -> 0.079617937 | Q83: =Q57 -> 0.078608933
B85: CapEx | L85: =L60 -> 59612 | M85: =M60 -> 76684.249 | N85: =N60 -> 86008.94 | O85: =O60 -> 91444.552 | P85: =P60 -> 97215.974 | Q85: =Q60 -> 109688.26
B86: % of sales | L86: =L61 -> 0.093781759 | M86: =M61 -> 0.10865347 | N86: =N61 -> 0.10958968 | O86: =O61 -> 0.10551777 | P86: =P61 -> 0.10185592 | Q86: =Q61 -> 0.10387972
B88: Change in NWC | L88: =L63 -> -6898 | M88: =M63 -> -11064.85 | N88: =N63 -> -20246.247 | O88: =O63 -> -19592.903 | P88: =P63 -> -18137.108 | Q88: =Q63 -> -19838.074
B89: % of sales | L89: =L64 -> -0.010851952 | M89: =M64 -> -0.015677722 | N89: =N64 -> -0.025797082 | O89: =O64 -> -0.022608231 | P89: =P64 -> -0.01900276 | Q89: =Q64 -> -0.018787549
B91: Unlevered FCF | L91: =L80+L82-L85-L88 -> 48177.691 | M91: =M80+M82-M85-M88 -> 54304.862 | N91: =N80+N82-N85-N88 -> 78108.907 | O91: =O80+O82-O85-O88 -> 95485.261 | P91: =P80+P82-P85-P88 -> 110448.01 | Q91: =Q80+Q82-Q85-Q88 -> 125111.18
B92: PV of UFCF | L92: =(L91*L94)/(1+wacc)^L95 -> 15842.828 | M92: =M91/(1+wacc)^M95 -> 50743.293 | N92: =N91/(1+wacc)^N95 -> 67280.377 | O92: =O91/(1+wacc)^O95 -> 75817.964 | P92: =P91/(1+wacc)^P95 -> 80842.845 | Q92: =Q91/(1+wacc)^Q95 -> 84416.576
B94: Stub | L94: =YEARFRAC(L5,L6) -> 0.33333333
B95: Discount Period | L95: =L94/2 -> 0.16666667 | M95: =L94+0.5 -> 0.83333333 | N95: =M95+1 -> 1.8333333 | O95: =N95+1 -> 2.8333333 | P95: =O95+1 -> 3.8333333 | Q95: =P95+1 -> 4.8333333
B97: Terminal Value | Q97: =(Q91*(1+tgr))/(wacc-tgr) -> 2144249
B98: PV of Terminal Value | Q98: =Q97/(1+wacc)^Q95 -> 1446794.5
B100: Enterprise Value | Q100: =SUM(L92:Q92,Q98) -> 1821738.3
B101: (+) Cash | Q101: =71178+17914 -> 89092
B102: (-) Debt | Q102: 54889
B103: Equity Value | Q103: =Q100+Q101-Q102 -> 1855941.3
B105: FDSO | Q105: =Shares!E14 -> 10876.067
B106: Implied Share Price | Q106: =Q103/Q105 -> 170.64453

Sheet WACC
B2: WACC
B4: WACC = % of equity x cost of equity + % of debt x cost of debt x (1 - Tax Rate)
B5: Cost of equity = Risk free rate + Beta x Market Risk Premium
A7: x | B7: WACC
B8: Market Cap | F8: 1873000
B9: % of Equity | F9: =F8/$F$20 -> 0.97152896
B10: Cost of Equity | F10: =F11+F12*F13 -> 0.08578
B11: Risk Free Rate | F11: 0.03909
B12: Beta | F12: 1.15
B13: Market Risk Premium | F13: 0.0406
B15: Debt | F15: 54889
B16: % of Debt | F16: =F15/$F$20 -> 0.028471037
B17: Cost of Debt | F17: =1233*2/F15 -> 0.044927035
B18: Tax Rate | F18: =DCF!L52 -> 0.1774763
B20: Total | F20: =F8+F15 -> 1927889
A22: x | B22: WACC | F22: =F9*F10+(F16*F17*(1-F18)) -> 0.08438986

Sheet Shares
B2: Diluted Share Count Calculation
A4: x | B4: Full Diluted Shares
B6: Current Stock Price | E6: 178.5
B7: Basic shares outstanding (latest filing) | E7: 10495.567
B8: In-the-money exercisable options | E8: =E30 -> 0
B9: Total proceeds ($mm) | E9: =SUMPRODUCT(D19:D28,E19:E28) -> 0
B10: Total shares repurchased (mm) | E10: =E9/E6 -> 0
B11: Net dilutive options | E11: =E8-E10 -> 0
B12: Dilutive impact of shares from other securities | E12: 380.5
B14: Net diluted shares outstanding | E14: =E7+E11+E12 -> 10876.067
A16: x | B16: Options outstanding
C18: Outstanding | D18: Exercise price | E18: Dilutive Shares
B19: 1 | E19: =IF(D19<$E$6,C19) -> 0
B20: =B19+1 -> 2 | E20: =IF(D20<$E$6,C20) -> 0
B21: =B20+1 -> 3 | E21: =IF(D21<$E$6,C21) -> 0
B22: =B21+1 -> 4 | E22: =IF(D22<$E$6,C22) -> 0
B23: =B22+1 -> 5 | E23: =IF(D23<$E$6,C23) -> 0
B24: =B23+1 -> 6 | E24: =IF(D24<$E$6,C24) -> 0
B25: =B24+1 -> 7 | E25: =IF(D25<$E$6,C25) -> 0
B26: =B25+1 -> 8 | E26: =IF(D26<$E$6,C26) -> 0
B27: =B26+1 -> 9 | E27: =IF(D27<$E$6,C27) -> 0
B28: =B27+1 -> 10 | E28: =IF(D28<$E$6,C28) -> 0
A30: x | B30: Total | E30: =SUM(E19:E28) -> 0

Sheet Segments
A1: AMZN-US
A2: Geographic Segments (M)
B3: CY '14 | C3: CY '15 | D3: CY '16 | E3: CY '17 | F3: CY '18 | G3: CY '19 | H3: CY '20 | I3: CY '21 | J3: CY '22 | K3: CY '23 | L3: CY '24E | M3: CY '25E | N3: CY '26E | O3: CY '27E | P3: CY '28E | Q3: CY '29E
B4: Dec '14 | C4: Dec '15 | D4: Dec '16 | E4: Dec '17 | F4: Dec '18 | G4: Dec '19 | H4: Dec '20 | I4: Dec '21 | J4: Dec '22 | K4: Dec '23 | L4: Dec '24E | M4: Dec '25E | N4: Dec '26E | O4: Dec '27E | P4: Dec '28E | Q4: Dec '29E
A5: Sales | B5: 88988 | C5: 107006 | D5: 135987 | E5: 177866 | F5: 232887 | G5: 280522 | H5: 386064 | I5: 469822 | J5: 513983 | K5: 574785 | L5: 635548 | M5: 704509 | N5: 779688 | O5: 858282 | P5: 942468 | Q5: 1029190
A6: North America | B6: 55469 | C6: 63708 | D6: 79785 | E6: 106110 | F6: 141366 | G6: 170773 | H6: 236282 | I6: 279833 | J6: 315880 | K6: 352828 | L6: 386647 | M6: 423461 | N6: 461471 | O6: 497416 | P6: 546306 | Q6: 590847
A7: - NA Other | B7: - | C7: - | D7: 1318 | E7: - | F7: - | G7: - | H7: - | I7: - | J7: 4247 | K7: - | L7: 5380 | M7: - | N7: - | O7: - | P7: - | Q7: -
A8: International | B8: 33519 | C8: 35418 | D8: 43983 | E8: 54297 | F8: 65866 | G8: 74723 | H8: 104412 | I8: 127787 | J8: 118007 | K8: 131200 | L8: 141444 | M8: 154680 | N8: 171709 | O8: 192631 | P8: 199416 | Q8: 215930
A9: AWS-Geo | B9: - | C9: 7880 | D9: 12219 | E9: 17459 | F9: 25655 | G9: 35026 | H9: 45370 | I9: 62202 | J9: 80096 | K9: 90757 | L9: 107555 | M9: 127628 | N9: 151647 | O9: 176580 | P9: 208724 | Q9: 249139
A11: Operating Income | B11: 178 | C11: 2233 | D11: 4186 | E11: 4106 | F11: 12421 | G11: 14541 | H11: 22899 | I11: 24879 | J11: 12248 | K11: 36852 | L11: 62364.9 | M11: 76519.4 | N11: 95065 | O11: 119029 | P11: 143146 | Q11: 174540
A12: North America | B12: 2105 | C12: 2751 | D12: 4099 | E12: 2837 | F12: 7267 | G12: 7033 | H12: 8651 | I12: 7271 | J12: -2847 | K12: 14877 | L12: 23233.5 | M12: 31059.3 | N12: 34190 | O12: - | P12: - | Q12: -
A13: - NA Media | B13: - | C13: - | D13: - | E13: - | F13: - | G13: - | H13: - | I13: - | J13: -2847 | K13: - | L13: - | M13: - | N13: - | O13: - | P13: - | Q13: -
A14: International | B14: -297 | C14: -91 | D14: -477 | E14: -3062 | F14: -2142 | G14: -1693 | H14: 717 | I14: -924 | J14: -7746 | K14: -2656 | L14: 1765.17 | M14: 3899.91 | N14: 9726 | O14: - | P14: - | Q14: -
A15: AWS-Geo | B15: - | C15: 1863 | D15: 3706 | E15: 4331 | F15: 7296 | G15: 9201 | H15: 13531 | I15: 18532 | J15: 22841 | K15: 24631 | L15: 37271.5 | M15: 42816.2 | N15: 53907.1 | O15: 70418.5 | P15: 85067.5 | Q15: 102298
A16: WFM- Geo | B16: - | C16: - | D16: - | E16: - | F16: - | G16: - | H16: - | I16: 495.175 | J16: 568.89 | K16: - | L16: - | M16: - | N16: - | O16: - | P16: - | Q16: -
A18: EBITDA | B18: 6553 | C18: 10805 | D18: 15440 | E18: 20007 | F18: 33476 | G18: 43245 | H18: 57284 | I18: 71994 | J18: 73836 | K18: 109538 | L18: 137679 | M18: 159786 | N18: 184965 | O18: 217623 | P18: 248736 | Q18: 289356
A19: North America | B19: - | C19: - | D19: - | E19: 7463 | F19: 13492 | G19: 16504 | H19: 17413 | I19: 22762 | J19: 17894 | K19: 41189 | L19: 47377 | M19: 53874 | N19: - | O19: - | P19: - | Q19: -
A20: International | B20: - | C20: - | D20: - | E20: 1945 | F20: - | G20: 5921 | H20: 7269 | I20: 14485 | J20: 14198 | K20: 16832 | L20: 25226 | M20: 28198 | N20: - | O20: - | P20: - | Q20: -
A21: AWS-Geo | B21: - | C21: - | D21: - | E21: 9128 | F21: 14189 | G21: 18239.6 | H21: 22953.5 | I21: 31239 | J21: 37506 | K21: 46916 | L21: 65410.5 | M21: 76791.5 | N21: 99377 | O21: 118602 | P21: 140497 | Q21: 165221

Sheet IS
A1: Amazon.com, Inc. (AMZN)
A2: $172.12
A5: Amazon.com, Inc.
A6: AMZN 023135106 2000019 NASDAQ Common stock
A7: Source: FactSet Fundamentals
B8: DEC '14 | C8: DEC '15 | D8: DEC '16 | E8: DEC '17 | F8: DEC '18 | G8: DEC '19 | H8: DEC '20 | I8: DEC '21 | J8: DEC '22 | K8: DEC '23 | L8: JUN '24
L9: LTM
A10: Sales | B10: 88988 | C10: 107006 | D10: 135987 | E10: 177866 | F10: 232887 | G10: 280522 | H10: 386064 | I10: 469822 | J10: 513983 | K10: 574785 | L10: 604334
A11: Cost of Goods Sold (COGS) incl. D&A | B11: 62752 | C11: 71651 | D11: 88265 | E11: 111934 | F11: 139156 | G11: 165536 | H11: 233307 | I11: 272344 | J11: 288831 | K11: 304739 | L11: 313993
A12: COGS excluding D&A | B12: 59530 | C12: 67109 | D12: 82212 | E12: 103282 | F12: 123815 | G12: 143747 | H12: 208056 | I12: 238048 | J12: 246910 | K12: 256076 | L12: 264320
A13: Depreciation & Amortization Expense | B13: 3222 | C13: 4542 | D13: 6053 | E13: 8652 | F13: 15341 | G13: 21789 | H13: 25251 | I13: 34296 | J13: 41921 | K13: 48663 | L13: 49673
A14: Depreciation | B14: 3041 | C14: 4314 | D14: 5766 | E14: 8286 | F14: 14866 | G14: 21224 | H14: 24742 | I14: 33784 | J14: 41317 | K14: 47957
A15: Amortization of Intangibles | B15: 181 | C15: 228 | D15: 287 | E15: 366 | F15: 475 | G15: 565 | H15: 509 | I15: 512 | J15: 604 | K15: 706
A16: Gross Income | B16: 26236 | C16: 35355 | D16: 47722 | E16: 65932 | F16: 93731 | G16: 114986 | H16: 152757 | I16: 197478 | J16: 225152 | K16: 270046 | L16: 290341
A17: SG&A Expense | B17: 25925 | C17: 32951 | D17: 43369 | E17: 61612 | F17: 81014 | G17: 100244 | H17: 129933 | I17: 172537 | J17: 211641 | K17: 232427 | L17: 235242
A18: Research & Development | B18: 9275 | C18: 12540 | D18: 16085 | E18: 22620 | F18: 28837 | G18: 35931 | H18: 42740 | I18: 56052 | J18: 73213 | K18: 85622 | L18: 85969
A19: Other SG&A | B19: 16650 | C19: 20411 | D19: 27284 | E19: 38992 | F19: 52177 | G19: 64313 | H19: 87193 | I19: 116485 | J19: 138428 | K19: 146805 | L19: 149273
A20: EBIT (Operating Income) | B20: 311 | C20: 2404 | D20: 4353 | E20: 4320 | F20: 12717 | G20: 14742 | H20: 22824 | I20: 24941 | J20: 13511 | K20: 37619 | L20: 55099
A21: Nonoperating Income - Net | B21: -212 | C21: -377 | D21: -44 | E21: 225 | F21: 92 | G21: 823 | H21: 1501 | I21: 2178 | J21: -1078 | K21: 2110 | L21: 2758
A22: Nonoperating Interest Income | B22: 39 | C22: 50 | D22: 100 | E22: 202 | F22: 440 | G22: 832 | H22: 555 | I22: 448 | J22: 989 | K22: 2949 | L22: 3850
A23: Other Income (Expense) | B23: -251 | C23: -427 | D23: -144 | E23: 23 | F23: -348 | G23: -9 | H23: 946 | I23: 1730 | J23: -2067 | K23: -839 | L23: -1092
A24: Interest Expense | B24: 210 | C24: 459 | D24: 484 | E24: 848 | F24: 1417 | G24: 1600 | H24: 1647 | I24: 1809 | J24: 2367 | K24: 3182 | L24: 2752
A25: Gross Interest Expense | B25: 210 | C25: 459 | D25: 484 | E25: 848 | F25: 1417 | G25: 1600 | H25: 1647 | I25: 1809 | J25: 2367 | K25: 3182 | L25: 2752
A26: Unusual Expense - Net | D26: -67 | E26: -109 | F26: 131 | G26: -11 | H26: -1500 | I26: -12841 | J26: 16002 | K26: -1010 | L26: 1002
A27: Unrealized Valuation Gain/Loss | D27: 67 | E27: 109 | F27: -131 | G27: 11 | H27: 1500 | I27: 12841 | J27: -16002 | K27: 1010 | L27: -832
A28: Investments | I28: 11526 | J28: -13870 | K28: 984 | L28: -518
A29: Hedges/Derivatives | D29: 67 | E29: 109 | F29: -131 | G29: 11 | H29: 1500 | I29: 1315 | J29: -2132 | K29: 26 | L29: -314
A30: Pretax Income | B30: -111 | C30: 1568 | D30: 3892 | E30: 3806 | F30: 11261 | G30: 13976 | H30: 24178 | I30: 38151 | J30: -5936 | K30: 37557 | L30: 54103
A31: Income Taxes | B31: 167 | C31: 950 | D31: 1425 | E31: 769 | F31: 1197 | G31: 2374 | H31: 2863 | I31: 4791 | J31: -3217 | K31: 7120 | L31: 9602
A32: Income Taxes - Current Domestic | B32: 279 | C32: 452 | D32: 1344 | E32: 74 | F32: 193 | G32: 438 | H32: 2461 | I32: 2892 | J32: 3249 | K32: 10810
A33: Income Taxes - Current Foreign | B33: 204 | C33: 417 | D33: 327 | E33: 724 | F33: 563 | G33: 1140 | H33: 956 | I33: 2209 | J33: 1682 | K33: 2186
A34: Income Taxes - Deferred Domestic | B34: -136 | C34: 302 | D34: 85 | E34: -228 | F34: 570 | G34: 922 | H34: -341 | I34: -23 | J34: -7988 | K34: -6003
A35: Income Taxes - Deferred Foreign | B35: -180 | C35: -221 | D35: -331 | E35: 199 | F35: -129 | G35: -126 | H35: -213 | I35: -287 | J35: -160 | K35: 127
A36: Equity in Earnings of Affiliates | B36: 37 | C36: -22 | D36: -96 | E36: -4 | F36: 9 | G36: -14 | H36: 16 | I36: 4 | J36: -3 | K36: -12 | L36: -82
A37: Consolidated Net Income | B37: -241 | C37: 596 | D37: 2371 | E37: 3033 | F37: 10073 | G37: 11588 | H37: 21331 | I37: 33364 | J37: -2722 | K37: 30425 | L37: 44419
A38: Net Income | B38: -241 | C38: 596 | D38: 2371 | E38: 3033 | F38: 10073 | G38: 11588 | H38: 21331 | I38: 33364 | J38: -2722 | K38: 30425 | L38: 44419
A39: Net Income available to Common | B39: -241 | C39: 596 | D39: 2371 | E39: 3033 | F39: 10073 | G39: 11588 | H39: 21331 | I39: 33364 | J39: -2722 | K39: 30425 | L39: 44419
A40: Per Share
A41: EPS (recurring) | B41: -0.026082 | C41: 0.062474 | D41: 0.240093 | E41: 0.299868 | F41: 1.01647 | G41: 1.148839 | H41: 1.988333 | I41: 2.366534 | J41: 0.832211 | K41: 2.832444 | L41: 4.213709
A42: EPS (basic) | B42: -0.026 | C42: 0.064 | D42: 0.2501 | E42: 0.316 | F42: 1.034 | G42: 1.1729 | H42: 2.1331 | I42: 3.2968 | J42: -0.2672 | K42: 2.9527 | L42: 4.2774
A43: Basic Shares Outstanding | B43: 9240 | C43: 9340 | D43: 9480 | E43: 9600 | F43: 9740 | G43: 9880 | H43: 10000 | I43: 10120 | J43: 10189 | K43: 10304 | L43: 10447
A44: Total Shares Outstanding | B44: 9300 | C44: 9420 | D44: 9540 | E44: 9680 | F44: 9820 | G44: 9960 | H44: 10060 | I44: 10180 | J44: 10242 | K44: 10383 | L44: 10490
A45: EPS (diluted) | B45: -0.026 | C45: 0.0625 | D45: 0.245 | E45: 0.3075 | F45: 1.0073 | G45: 1.1496 | H45: 2.0913 | I45: 3.2392 | J45: -0.2672 | K45: 2.8998 | L45: 4.1739
A46: Diluted Shares Outstanding | B46: 9240 | C46: 9540 | D46: 9680 | E46: 9860 | F46: 10000 | G46: 10080 | H46: 10200 | I46: 10300 | J46: 10189 | K46: 10492 | L46: 10708
A47: Total Shares Outstanding | B47: 9300 | C47: 9420 | D47: 9540 | E47: 9680 | F47: 9820 | G47: 9960 | H47: 10060 | I47: 10180 | J47: 10242 | K47: 10383 | L47: 10490
A48: Earnings Persistence | B48: 63.042 | C48: 70.868 | D48: 74.055 | E48: 57.155 | F48: 76.614 | G48: 74.36 | H48: 77.338 | I48: 68.89 | J48: 79.504 | K48: 85.315
A49: EBITDA
A50: EBITDA | B50: 3533 | C50: 6946 | D50: 10406 | E50: 12972 | F50: 28058 | G50: 36531 | H50: 48075 | I50: 59237 | J50: 55432 | K50: 86282 | L50: 104772
A51: EBIT | B51: 311 | C51: 2404 | D51: 4353 | E51: 4320 | F51: 12717 | G51: 14742 | H51: 22824 | I51: 24941 | J51: 13511 | K51: 37619 | L51: 55099
A52: Depreciation & Amortization Expense | B52: 3222 | C52: 4542 | D52: 6053 | E52: 8652 | F52: 15341 | G52: 21789 | H52: 25251 | I52: 34296 | J52: 41921 | K52: 48663 | L52: 49673
A53: All figures in millions of U.S. Dollar except per share items.

Sheet CFS
A1: Amazon.com, Inc. (AMZN)
A2: $172.12
A5: Amazon.com, Inc.
A6: AMZN 023135106 2000019 NASDAQ Common stock
A7: Source: FactSet Fundamentals
B8: DEC '14 | C8: DEC '15 | D8: DEC '16 | E8: DEC '17 | F8: DEC '18 | G8: DEC '19 | H8: DEC '20 | I8: DEC '21 | J8: DEC '22 | K8: DEC '23 | L8: JUN '24
L9: LTM
A10: Operating Activities
A11: Net Income / Starting Line | B11: -241 | C11: 596 | D11: 2371 | E11: 3033 | F11: 10073 | G11: 11588 | H11: 21331 | I11: 33364 | J11: -2722 | K11: 30425 | L11: 44419
A12: Depreciation, Depletion & Amortization | B12: 4187 | C12: 5646 | D12: 7482 | E12: 10933 | F12: 15341 | G12: 21789 | H12: 25251 | I12: 34296 | J12: 41921 | K12: 48663 | L12: 49673
A13: Depreciation and Depletion | F13: 14866 | G13: 21224 | H13: 24742 | I13: 33784 | J13: 41317 | K13: 47957
A14: Amortization of Intangible Assets | F14: 475 | G14: 565 | H14: 509 | I14: 512 | J14: 604 | K14: 706
A15: Deferred Taxes & Investment Tax Credit | B15: -316 | C15: 81 | D15: -246 | E15: -29 | F15: 441 | G15: 796 | H15: -554 | I15: -310 | J15: -8148 | K15: -5876 | L15: -4383
A16: Deferred Taxes | B16: -316 | C16: 81 | D16: -246 | E16: -29 | F16: 441 | G16: 796 | H16: -554 | I16: -310 | J16: -8148 | K16: -5876 | L16: -4383
A17: Other Funds | B17: 2238 | C17: 3040 | D17: 2920 | E17: 4670 | F17: 5911 | G17: 6779 | H17: 6555 | I17: -1412 | J17: 36587 | K17: 23275 | L17: 25141
A18: Funds from Operations | B18: 5868 | C18: 9363 | D18: 12527 | E18: 18607 | F18: 31766 | G18: 40952 | H18: 52583 | I18: 65938 | J18: 67638 | K18: 96487 | L18: 114850
A19: Changes in Working Capital | B19: 974 | C19: 2557 | D19: 3916 | E19: -173 | F19: -1043 | G19: -2438 | H19: 13481 | I19: -19611 | J19: -20886 | K19: -11541 | L19: -6898
A20: Receivables | B20: -1039 | C20: -1755 | D20: -3367 | E20: -4786 | F20: -4615 | G20: -7681 | H20: -8169 | I20: -18163 | J20: -21897 | K20: -8348 | L20: -3227
A21: Inventories | B21: -1193 | C21: -2187 | D21: -1426 | E21: -3583 | F21: -1314 | G21: -3278 | H21: -2849 | I21: -9487 | J21: -2592 | K21: 1449 | L21: 2142
A22: Accounts Payable | B22: 1759 | C22: 4294 | D22: 5030 | E22: 7175 | F22: 3263 | G22: 8193 | H22: 17480 | I22: 3602 | J22: 2945 | K22: 5473 | L22: 8431
A23: Other Accruals | B23: 706 | C23: 913 | D23: 1724 | E23: 283 | F23: 472 | G23: -1383 | H23: 5754 | I23: 2123 | J23: -1558 | K23: -2428 | L23: -1802
A24: Other Assets/Liabilities | B24: 741 | C24: 1292 | D24: 1955 | E24: 738 | F24: 1151 | G24: 1711 | H24: 1265 | I24: 2314 | J24: 2216 | K24: -7687 | L24: -12442
A25: Net Operating Cash Flow | B25: 6842 | C25: 11920 | D25: 16443 | E25: 18434 | F25: 30723 | G25: 38514 | H25: 66064 | I25: 46327 | J25: 46752 | K25: 84946 | L25: 107952
A26: Investing Activities
A27: Capital Expenditures | B27: -4893 | C27: -4589 | D27: -6737 | E27: -11955 | F27: -13427 | G27: -16861 | H27: -40140 | I27: -61053 | J27: -63645 | K27: -52729 | L27: -59612
A28: Capital Expenditures (Fixed Assets) | B28: -4893 | C28: -4589 | D28: -6737 | E28: -11955 | F28: -13427 | G28: -16861 | H28: -40140 | I28: -61053 | J28: -63645 | K28: -52729 | L28: -59612
A29: Net Assets from Acquisitions | B29: -979 | C29: -795 | D29: -116 | E29: -13972 | F29: -2186 | G29: -2461 | H29: -2325 | I29: -1985 | J29: -8316 | K29: -5839 | L29: -5935
A30: Sale of Fixed Assets & Businesses | B30: 0 | C30: 0 | D30: 0 | E30: 1897 | F30: 2104 | G30: 4172 | H30: 5096 | I30: 5657 | J30: 5324 | K30: 4596 | L30: 4633
A31: Purchase/Sale of Investments | B31: 807 | C31: -1066 | D31: -3023 | E31: -3789 | F31: 1140 | G31: -9131 | H31: -22242 | I31: -773 | J31: 29036 | K31: 4139 | L31: -3440
A32: Purchase of Investments | B32: 2542 | C32: 4091 | D32: 7756 | E32: 13777 | F32: 7100 | G32: 31812 | H32: 72479 | I32: 60157 | J32: 2565 | K32: 1488 | L32: 11058
A33: Sale/Maturity of Investments | B33: 3349 | C33: 3025 | D33: 4733 | E33: 9988 | F33: 8240 | G33: 22681 | H33: 50237 | I33: 59384 | J33: 31601 | K33: 5627 | L33: 7618
A34: Net Investing Cash Flow | B34: -5065 | C34: -6450 | D34: -9876 | E34: -27819 | F34: -12369 | G34: -24281 | H34: -59611 | I34: -58154 | J34: -37601 | K34: -49833 | L34: -64354
A35: Financing Activities
A36: Change in Capital Stock | B36: 0 | C36: 0 | D36: 0 | E36: 0 | F36: 0 | G36: 0 | H36: 0 | I36: 0 | J36: -6000 | K36: 0 | L36: 0
A37: Repurchase of Common & Preferred Stk. | B37: 0 | C37: 0 | D37: 0 | E37: 0 | F37: 0 | G37: 0 | H37: 0 | I37: 0 | J37: -6000 | K37: 0 | L37: 0
A38: Issuance/Reduction of Debt, Net | B38: 4426 | C38: -3882 | D38: -3740 | E38: 9860 | F38: -7686 | G38: -10066 | H38: -1104 | I38: 6291 | J38: 15718 | K38: -15879 | L38: -21440
A39: Change in Current Debt | B39: 0 | C39: 0 | D39: 0 | E39: 0 | F39: 0 | G39: 0 | H39: 619 | I39: 203 | J39: 3999 | K39: -7548 | L39: -13253
A40: Change in Long-Term Debt | B40: 4426 | C40: -3882 | D40: -3740 | E40: 9860 | F40: -7686 | G40: -10066 | H40: -1723 | I40: 6088 | J40: 11719 | K40: -8331 | L40: -8187
A41: Issuance of Long-Term Debt | B41: 6359 | C41: 353 | D41: 621 | E41: 16231 | F41: 768 | G41: 2273 | H41: 10525 | I41: 19003 | J41: 21166 | K41: 0 | L41: 0
A42: Reduction in Long-Term Debt | B42: -1933 | C42: -4235 | D42: -4361 | E42: -6371 | F42: -8454 | G42: -12339 | H42: -12248 | I42: -12915 | J42: -9447 | K42: -8331 | L42: -8187
A43: Other Funds | B43: 6 | C43: 119 | D43: 829 | E43: 0 | F43: 0 | G43: 0 | H43: 0 | I43: 0 | J43: 0 | K43: 0 | L43: 0
A44: Other Sources | B44: 6 | C44: 119 | D44: 829 | E44: 0 | F44: 0 | G44: 0 | H44: 0 | I44: 0 | J44: 0 | K44: 0 | L44: 0
A45: Net Financing Cash Flow | B45: 4432 | C45: -3763 | D45: -2911 | E45: 9860 | F45: -7686 | G45: -10066 | H45: -1104 | I45: 6291 | J45: 9718 | K45: -15879 | L45: -21440
A46: All Activities
A47: Exchange Rate Effect | B47: -310 | C47: -374 | D47: -212 | E47: 713 | F47: -351 | G47: 70 | H47: 618 | I47: -364 | J47: -1093 | K47: 403 | L47: -552
A48: Net Change in Cash | B48: 5899 | C48: 1333 | D48: 3444 | E48: 1188 | F48: 10317 | G48: 4237 | H48: 5967 | I48: -5900 | J48: 17776 | K48: 19637 | L48: 21606
A49: Free Cash Flow | B49: 1949 | C49: 7331 | D49: 9706 | E49: 6479 | F49: 17296 | G49: 21653 | H49: 25924 | I49: -14726 | J49: -16893 | K49: 32217 | L49: 48340
A50: Free Cash Flow per Share | B50: 0.210931 | C50: 0.768449 | D50: 1.002686 | E50: 0.657099 | F50: 1.7296 | G50: 2.148115 | H50: 2.541569 | I50: -1.429709 | J50: -1.657964 | K50: 3.070625 | L50: 4.514382
A51: Free Cash Flow Yield (%) | B51: 1.359309 | C51: 2.273887 | D51: 2.674293 | E51: 1.123756 | F51: 2.303108 | G51: 2.325001 | H51: 1.560714 | I51: -0.857566 | J51: -1.973767 | K51: 2.020946 | L51: 2.336032
A52: All figures in millions of U.S. Dollar except per share items.

Sheet CapEx
A1: AMZN-US
A2: Cash Flow (M)
B3: CY '14 | C3: CY '15 | D3: CY '16 | E3: CY '17 | F3: CY '18 | G3: CY '19 | H3: CY '20 | I3: CY '21 | J3: CY '22 | K3: CY '23 | L3: CY '24E | M3: CY '25E | N3: CY '26E | O3: CY '27E | P3: CY '28E | Q3: CY '29E
B4: Dec '14 | C4: Dec '15 | D4: Dec '16 | E4: Dec '17 | F4: Dec '18 | G4: Dec '19 | H4: Dec '20 | I4: Dec '21 | J4: Dec '22 | K4: Dec '23 | L4: Dec '24E | M4: Dec '25E | N4: Dec '26E | O4: Dec '27E | P4: Dec '28E | Q4: Dec '29E
A5: Capital Expenditures | B5: 4892 | C5: 4588 | D5: 6736 | E5: 10058 | F5: 11322 | G5: 12690 | H5: 35046 | I5: 55396 | J5: 58321 | K5: 52729 | L5: 65971.5 | M5: 71754.7 | N5: 71087 | O5: 80757.5 | P5: 84731.5 | Q5: 89516
A6: Free Cash Flow | B6: 1949 | C6: 7331 | D6: 9706 | E6: 8377 | F6: 19402 | G6: 25825 | H6: 31018 | I6: -9069 | J6: -11569 | K6: 36658 | L6: 55427.3 | M6: 69788.9 | N6: 98528.1 | O6: 126711 | P6: 149789 | Q6: 177525
A7: Unlevered Free Cash Flow | B7: 449 | C7: - | D7: - | E7: - | F7: - | G7: - | H7: - | I7: - | J7: - | K7: - | L7: - | M7: - | N7: - | O7: - | P7: - | Q7: -
A8: Cash Flow from Operations | B8: 6841 | C8: 11920 | D8: 16442 | E8: 18434 | F8: 30724 | G8: 38515 | H8: 66064 | I8: 46327 | J8: 46752 | K8: 84946 | L8: 114364 | M8: 142436 | N8: 172056 | O8: 210079 | P8: 244061 | Q8: 279962
A9: Cash Flow from Investing | B9: -5066 | C9: -6450 | D9: -9876 | E9: -27819 | F9: -12369 | G9: -24282 | H9: -59612 | I9: -58154 | J9: -37601 | K9: -49833 | L9: -70567.5 | M9: -71130.6 | N9: -74942 | O9: -79012.8 | P9: -81779.3 | Q9: -85077.6
A10: Cash Flow from Financing | B10: 4433 | C10: -3763 | D10: -2911 | E10: 9861 | F10: -7687 | G10: -10066 | H10: -1104 | I10: 6291 | J10: 9718 | K10: -15879 | L10: -7287.05 | M10: -4106.33 | N10: -3515.48 | O10: -4625 | P10: -1125 | Q10: 0
